{
  "name": "Cedarskin Cuirass",
  "_id": "KPcedarskincuira",
  "effects": [],
  "folder": null,
  "flags": {
    "black-flag": {
      "relationship": {}
    }
  },
  "type": "gear",
  "img": "systems/dnd5e/icons/svg/items/equipment.svg",
  "system": {
    "activities": {},
    "uses": {},
    "description": {
      "value": "<p><em>Armor (Studded Leather), Very Rare (Requires Attunement)</em><br>This lightweight, fragrant piece is finely crafted of doeskin and reinforced with strips of woven cedar bark and rawhide. The armor is treated as <em>+1 studded leather</em>. In addition, while you wear it, you have advantage on any saving throws related to poison and disease, and difficult terrain doesn’t impede your movement.<br>Content licensed under the @UUID[Compendium.koboldpressogl-bf.koboldpressjournal.JournalEntry.KoboldPressOGL00.JournalEntryPage.KoboldPressOGLpg]{Open Game License}",
      "source": {
        "book": "WG4"
      }
    },
    "identifier": {
      "value": "cedarskin-cuirass"
    },
    "container": null,
    "price": {
      "value": 0,
      "denomination": "gp"
    },
    "quantity": 1,
    "rarity": "very rare",
    "weight": {
      "value": 0,
      "units": "pound"
    },
    "attunement": {},
    "type": {
      "category": "",
      "value": ""
    }
  },
  "_key": "!items!KPcedarskincuira"
}
