{
  "name": "Dragon Seed",
  "_id": "KPdragonseed0000",
  "effects": [],
  "folder": null,
  "flags": {
    "black-flag": {
      "relationship": {}
    }
  },
  "type": "consumable",
  "img": "systems/dnd5e/icons/svg/items/loot.svg",
  "system": {
    "activities": {},
    "uses": {},
    "description": {
      "value": "<p><em>Wondrous Item, Very Rare</em><br>When thrown, this illusion seed turns into a dragon of some kind, though the exact type is known only to its creator. Roll on the table below.<table><tr><th>d20</th><th>Dragon Type</th><th>Charisma DC</th></tr><tr><td>1–2</td><td>@UUID[Compendium.koboldpressogl-bf.koboldpressmonsters.Actor.KPlanterndragone]{Lantern dragonette}</td><td>8</td></tr><tr><td>3–4</td><td>@UUID[Compendium.koboldpressogl-bf.koboldpressmonsters.Actor.KPwinddragonwyrm]{Wind dragon wyrmling}</td><td>9</td></tr><tr><td>5–6</td><td>@UUID[Compendium.black-flag.npcs.Actor.ISXBZMqeLNEI8zmd]{White dragon wyrmling}</td><td>10</td></tr><tr><td>7</td><td>@UUID[Compendium.koboldpressogl-bf.koboldpressmonsters.Actor.KPlindwurm000000]{Lindwurm}</td><td>10</td></tr><tr><td>8</td><td>@UUID[Compendium.black-flag.npcs.Actor.GTo6rb03cdWAZ4lh]{Red dragon wyrmling}</td><td>11</td></tr><tr><td>9</td><td>@UUID[Compendium.black-flag.npcs.Actor.NS7UISvgtmDOQ9MI]{Young white dragon}</td><td>11</td></tr><tr><td>10</td><td>@UUID[Compendium.koboldpressogl-bf.koboldpressmonsters.Actor.KPyoungmithraldr]{Young mithral dragon}</td><td>12</td></tr><tr><td>11</td><td>@UUID[Compendium.black-flag.npcs.Actor.rABx4QexdSc6vTsq]{Young brass dragon}</td><td>13</td></tr><tr><td>12</td><td>@UUID[Compendium.black-flag.npcs.Actor.0V3Lr3QRumobWHx0]{Young copper dragon}</td><td>14</td></tr><tr><td>13</td><td>@UUID[Compendium.black-flag.npcs.Actor.V0hoY7QNVvQwQDCB]{Young blue dragon}</td><td>15</td></tr><tr><td>14</td><td>@UUID[Compendium.black-flag.npcs.Actor.3OZjOK8mayQUCVGq]{Young green dragon}</td><td>16</td></tr><tr><td>15</td><td>@UUID[Compendium.koboldpressogl-bf.koboldpressmonsters.Actor.KPyoungflamedrag]{Young flame dragon}</td><td>17</td></tr><tr><td>16</td><td>@UUID[Compendium.black-flag.npcs.Actor.U301vMUDHMsilO8e]{Young gold dragon}</td><td>18</td></tr><tr><td>17</td><td>@UUID[Compendium.black-flag.npcs.Actor.yhAnGtwttTdrbFxU]{Adult white dragon}</td><td>19</td></tr><tr><td>18</td><td>@UUID[Compendium.koboldpressogl-bf.koboldpressmonsters.Actor.KPadultmithraldr]{Adult mithral dragon}</td><td>20</td></tr><tr><td>19</td><td>@UUID[Compendium.black-flag.npcs.Actor.FuwI4sYfUqwJUCLZ]{Adult silver dragon}</td><td>21</td></tr><tr><td>20</td><td>@UUID[Compendium.black-flag.npcs.Actor.8ZGw45FNU52DyRyf]{Adult red dragon}</td><td>22</td></tr></table><br>The dragon created by the illusion seed considers you to be a friend, and it speaks with you and keeps you company for at least 24 hours. During that time, the dragon defends itself and may defend you. After each additional 24 hours, you must make a Charisma saving throw as shown on the table above. When the check fails, the illusory dragon vanishes.</table><br>Content licensed under the @UUID[Compendium.koboldpressogl-bf.koboldpressjournal.JournalEntry.KoboldPressOGL00.JournalEntryPage.KoboldPressOGLpg]{Open Game License}",
      "source": {
        "book": "BoET"
      }
    },
    "identifier": {
      "value": "dragon-seed"
    },
    "container": null,
    "price": {
      "value": 0,
      "denomination": "gp"
    },
    "quantity": 1,
    "rarity": "very rare",
    "weight": {
      "value": 0,
      "units": "pound"
    },
    "attunement": {
      "value": ""
    },
    "properties": [
      "magical"
    ],
    "type": {
      "category": ""
    }
  },
  "_key": "!items!KPdragonseed0000"
}
